ginx/__init__.py
ginx/runner.py
ginx/cli/__init__.py
ginx/cli/app.py
ginx/cli/execution.py
ginx/cli/registration.py
ginx/cli/commands/__init__.py
ginx/cli/commands/core.py
ginx/cli/commands/init.py
ginx/cli/commands/registry.py
ginx/cli/commands/run.py
ginx/cmd/__init__.py
ginx/config/__init__.py
ginx/config/discovery.py
ginx/config/loader.py
ginx/config/plugins.py
ginx/config/scripts.py
ginx/config/settings.py
ginx/config/validator.py
ginx/constants/__init__.py
ginx/init/__init__.py
ginx/init/ginx.py
ginx/plugins/__init__.py
ginx/plugins/example.py
ginx/plugins/version_sync/__init__.py
ginx/plugins/version_sync/commands.py
ginx/plugins/version_sync/core.py
ginx/plugins/version_sync/package_utils.py
ginx/plugins/version_sync/pypi_utils.py
ginx/plugins/version_sync/version_utils.py
ginx/utils/__init__.py
ginx/utils/command.py
ginx/utils/file.py
ginx/utils/format.py
ginx/utils/system.py
ginx-0.1.6.dist-info/METADATA
ginx-0.1.6.dist-info/WHEEL
ginx-0.1.6.dist-info/entry_points.txt
ginx-0.1.6.dist-info/top_level.txt
ginx-0.1.6.dist-info/RECORD
