Metadata-Version: 2.4
Name: ginx
Version: 0.1.6
Summary: A command-line script runner powered by YAML configuration
Author-email: Eric Kweyunga <maverickweyunga@gmail.com>
Maintainer-email: Eric Kweyunga <maverickweyunga@gmail.com>
License-Expression: MIT
Project-URL: Homepage, https://github.com/erickweyunga/ginx
Project-URL: Documentation, https://github.com/erickweyunga/ginx#readme
Project-URL: Repository, https://github.com/erickweyunga/ginx.git
Project-URL: Bug Reports, https://github.com/erickweyunga/ginx/issues
Project-URL: Changelog, https://github.com/erickweyunga/ginx/blob/main/CHANGELOG.md
Keywords: cli,automation,scripts,yaml,runner,task
Classifier: Development Status :: 4 - Beta
Classifier: Environment :: Console
Classifier: Intended Audience :: Developers
Classifier: Operating System :: OS Independent
Classifier: Programming Language :: Python :: 3
Classifier: Programming Language :: Python :: 3.8
Classifier: Programming Language :: Python :: 3.9
Classifier: Programming Language :: Python :: 3.10
Classifier: Programming Language :: Python :: 3.11
Classifier: Programming Language :: Python :: 3.12
Classifier: Topic :: Software Development :: Build Tools
Classifier: Topic :: System :: Systems Administration
Classifier: Topic :: Utilities
Requires-Python: >=3.8
Requires-Dist: typer>=0.9.0
Requires-Dist: PyYAML>=6.0
Requires-Dist: rich>=13.0.0
Requires-Dist: packaging>=25.0.0
Provides-Extra: dev
Requires-Dist: pytest>=7.0.0; extra == "dev"
Requires-Dist: pytest-cov>=4.0.0; extra == "dev"
Requires-Dist: black>=23.0.0; extra == "dev"
Requires-Dist: isort>=5.12.0; extra == "dev"
Requires-Dist: flake8>=6.0.0; extra == "dev"
Requires-Dist: mypy>=1.0.0; extra == "dev"
Requires-Dist: pre-commit>=3.0.0; extra == "dev"
Requires-Dist: packaging>=25.0.0; extra == "dev"
Requires-Dist: dotenv>=0.9.9; extra == "dev"
Provides-Extra: test
Requires-Dist: pytest>=7.0.0; extra == "test"
Requires-Dist: pytest-cov>=4.0.0; extra == "test"
Requires-Dist: pytest-mock>=3.10.0; extra == "test"
